human_errors/__init__.py
human_errors/base_renderer.py
human_errors/json_renderer.py
human_errors/parse_file.py
human_errors/renderers/default.py
human_errors/renderers/miette.py
human_errors/stack_utils.py
human_errors/toml_renderer.py
human_errors/utils.py
human_errors/yaml_renderer.py
human_errors-0.0.3.dist-info/WHEEL
human_errors-0.0.3.dist-info/entry_points.txt
human_errors-0.0.3.dist-info/METADATA
human_errors-0.0.3.dist-info/RECORD
