Metadata-Version: 2.3
Name: human-errors
Version: 0.0.3
Summary: everyone makes mistakes, show the errors to them 
Keywords: exception,config,json,yaml,toml
Author: NSPC911
License: MIT
Classifier: Development Status :: 4 - Beta
Classifier: License :: OSI Approved :: MIT License
Classifier: Programming Language :: Python :: 3.13
Classifier: Topic :: Utilities
Classifier: Topic :: File Formats
Classifier: Topic :: File Formats :: JSON
Classifier: Topic :: Text Processing
Requires-Dist: poethepoet>=0.37.0
Requires-Dist: rich>=14.2.0
Requires-Python: >=3.12
Project-URL: Issues, https://github.com/NSPC911/human-errors/issues
Project-URL: Source, https://github.com/NSPC911/human-errors
